{
  "assignment0": {
    "title": "Prework",
    "URL": "https://github.com/nss-nightclass-projects/homework/blob/master/prework.md",
    "dueDate": "2/12/18",
    "isAssigned": "true",
    "isGithub": "false",
    "assignedNumber": 1,
    "topic": "",
    "notes": "PREWORK, PREWORK, PREWORK, Hey have you done your PREWORK?"
  },
  "assignment1": {
    "title": "HW Week 1",
    "URL": "https://github.com/nss-nightclass-projects/e7-homework/blob/master/week01.md",
    "dueDate": "2/19/18",
    "isAssigned": "true",
    "isGithub": "false",
    "assignedNumber": 2,
    "topic": "",
    "notes": "Please do the steps in order."
  },
  "assignment2": {
    "title": "CSS Zen Garden",
    "URL": "",
    "dueDate": "2/26/18",
    "isAssigned": "true",
    "isGithub": "true",
    "assignedNumber": 3,
    "topic": "HTML/CSS",
    "notes": "*** Study Group ***"
  },
  "assignment3": {
    "title": "Blog Post",
    "URL": "https://github.com/nss-nightclass-projects/homework/blob/master/blog.md",
    "dueDate": "2/27/18",
    "isAssigned": "true",
    "isGithub": "true",
    "assignedNumber": 4,
    "topic": "",
    "notes": "Week 1: HTML, CSS, Git, Github"
  },
  "assignment4": {
    "title": "Personal Site #1",
    "URL": "https://github.com/nss-nightclass-projects/personal-site-instructions/blob/master/personal-bio-site-1.md",
    "dueDate": "2/27/18",
    "isAssigned": "true",
    "isGithub": "true",
    "assignedNumber": 5,
    "topic": "",
    "notes": ""
  },
  "assignment5": {
    "title": "Personal Site #2",
    "URL": "https://github.com/nss-nightclass-projects/personal-site-instructions/blob/master/personal-bio-site-2.md",
    "dueDate": "2/27/18",
    "isAssigned": "true",
    "isGithub": "true",
    "assignedNumber": 6,
    "topic": "",
    "notes": "we will cover this material on 2/24"
  }
}